_ebddocx2table_version.py
ebddocx2table/__init__.py
ebddocx2table/docxtableconverter.py
ebddocx2table/py.typed
ebddocx2table-0.0.9.dist-info/METADATA
ebddocx2table-0.0.9.dist-info/WHEEL
ebddocx2table-0.0.9.dist-info/licenses/LICENSE
ebddocx2table-0.0.9.dist-info/RECORD
