Metadata-Version: 2.1
Name: ebddocx2table
Version: 0.0.9
Summary: A scraper to library to scrape .docx files with 'Entscheidungsbaumdiagramm' tables into a truely machine readable structure
Project-URL: Changelog, https://github.com/Hochfrequenz/ebddocx2table/releases
Project-URL: Homepage, https://github.com/Hochfrequenz/ebddocx2table
Author-email: Hochfrequenz Unternehmensberatung GmbH <info@hochfrequenz.de>
License: GPL
License-File: LICENSE
Keywords: EBD,Energiewirtschaft,Marktkommunikation
Classifier: Development Status :: 4 - Beta
Classifier: Environment :: Console
Classifier: Intended Audience :: Developers
Classifier: License :: OSI Approved :: GNU General Public License v3 (GPLv3)
Classifier: Operating System :: OS Independent
Classifier: Programming Language :: Python
Classifier: Programming Language :: Python :: 3 :: Only
Classifier: Programming Language :: Python :: 3.11
Classifier: Programming Language :: Python :: 3.12
Requires-Python: >=3.11
Requires-Dist: attrs
Requires-Dist: click
Requires-Dist: ebdtable2graph>=0.1.19
Requires-Dist: more-itertools
Requires-Dist: python-docx
